ded.py
ded-0.1.4.dist-info/entry_points.txt
ded-0.1.4.dist-info/WHEEL
ded-0.1.4.dist-info/METADATA
ded-0.1.4.dist-info/RECORD
