Metadata-Version: 2.1
Name: ded
Version: 0.1.4
Summary: Helm dependency deduplication post-renderer
Home-page: https://github.com/vduseev/ded
License: MIT
Keywords: helm,dependency,post-renderer,deduplication,subchart
Author: vduseev
Author-email: vagiz.d@gmail.com
Requires-Python: >=3.6,<4.0
Classifier: License :: OSI Approved :: MIT License
Classifier: Programming Language :: Python :: 3
Classifier: Programming Language :: Python :: 3.6
Classifier: Programming Language :: Python :: 3.7
Classifier: Programming Language :: Python :: 3.8
Requires-Dist: ruamel.yaml (>=0.16.10,<0.17.0)
Project-URL: Documentation, https://github.com/vduseev/ded
Project-URL: Repository, https://github.com/vduseev/ded
